categorical_embedder/__init__.py
categorical_embedder-0.1.dist-info/LICENSE.txt
categorical_embedder-0.1.dist-info/METADATA
categorical_embedder-0.1.dist-info/WHEEL
categorical_embedder-0.1.dist-info/top_level.txt
categorical_embedder-0.1.dist-info/RECORD
