Metadata-Version: 2.1
Name: categorical-embedder
Version: 0.1
Summary: Categorical Embedder is a python package that let's you convert your categorical variables into numeric via Neural Networks
Home-page: https://github.com/Shivanandroy/CategoricalEmbedder/
Author: Shivanand Roy
Author-email: Shivanandroy.official@gmail.com
License: UNKNOWN
Platform: UNKNOWN
Classifier: Programming Language :: Python :: 3
Classifier: License :: OSI Approved :: MIT License
Classifier: Operating System :: OS Independent
Requires-Dist: numpy
Requires-Dist: pandas
Requires-Dist: tensorflow
Requires-Dist: keras
Requires-Dist: tqdm
Requires-Dist: keras-tqdm
Requires-Dist: sklearn
